example/__init__.py
example/_version.py
example/main.py
example_package_chanshing-1.1.11.dist-info/LICENSE.md
example_package_chanshing-1.1.11.dist-info/METADATA
example_package_chanshing-1.1.11.dist-info/WHEEL
example_package_chanshing-1.1.11.dist-info/entry_points.txt
example_package_chanshing-1.1.11.dist-info/top_level.txt
example_package_chanshing-1.1.11.dist-info/RECORD
